odoo8_addon_web_widget_image_download-8.0.1.0.1.99.dev4-py2.7-nspkg.pth
odoo8_addon_web_widget_image_download-8.0.1.0.1.99.dev4.dist-info/DESCRIPTION.rst
odoo8_addon_web_widget_image_download-8.0.1.0.1.99.dev4.dist-info/METADATA
odoo8_addon_web_widget_image_download-8.0.1.0.1.99.dev4.dist-info/RECORD
odoo8_addon_web_widget_image_download-8.0.1.0.1.99.dev4.dist-info/WHEEL
odoo8_addon_web_widget_image_download-8.0.1.0.1.99.dev4.dist-info/metadata.json
odoo8_addon_web_widget_image_download-8.0.1.0.1.99.dev4.dist-info/namespace_packages.txt
odoo8_addon_web_widget_image_download-8.0.1.0.1.99.dev4.dist-info/top_level.txt
odoo_addons/web_widget_image_download/README.rst
odoo_addons/web_widget_image_download/__init__.py
odoo_addons/web_widget_image_download/__openerp__.py
odoo_addons/web_widget_image_download/i18n/ar.po
odoo_addons/web_widget_image_download/i18n/bg.po
odoo_addons/web_widget_image_download/i18n/bs.po
odoo_addons/web_widget_image_download/i18n/cs.po
odoo_addons/web_widget_image_download/i18n/da.po
odoo_addons/web_widget_image_download/i18n/en_GB.po
odoo_addons/web_widget_image_download/i18n/es.po
odoo_addons/web_widget_image_download/i18n/es_AR.po
odoo_addons/web_widget_image_download/i18n/es_CL.po
odoo_addons/web_widget_image_download/i18n/es_CO.po
odoo_addons/web_widget_image_download/i18n/es_CR.po
odoo_addons/web_widget_image_download/i18n/es_DO.po
odoo_addons/web_widget_image_download/i18n/es_EC.po
odoo_addons/web_widget_image_download/i18n/es_MX.po
odoo_addons/web_widget_image_download/i18n/es_PE.po
odoo_addons/web_widget_image_download/i18n/et.po
odoo_addons/web_widget_image_download/i18n/fa.po
odoo_addons/web_widget_image_download/i18n/fi.po
odoo_addons/web_widget_image_download/i18n/he.po
odoo_addons/web_widget_image_download/i18n/hr.po
odoo_addons/web_widget_image_download/i18n/hu.po
odoo_addons/web_widget_image_download/i18n/id.po
odoo_addons/web_widget_image_download/i18n/ja.po
odoo_addons/web_widget_image_download/i18n/ko.po
odoo_addons/web_widget_image_download/i18n/lt.po
odoo_addons/web_widget_image_download/i18n/lv.po
odoo_addons/web_widget_image_download/i18n/mk.po
odoo_addons/web_widget_image_download/i18n/mn.po
odoo_addons/web_widget_image_download/i18n/nb.po
odoo_addons/web_widget_image_download/i18n/nl_BE.po
odoo_addons/web_widget_image_download/i18n/pl.po
odoo_addons/web_widget_image_download/i18n/sk.po
odoo_addons/web_widget_image_download/i18n/sl.po
odoo_addons/web_widget_image_download/i18n/sr@latin.po
